MANIFEST.in
README.markdown
setup.py
pylibchorus/__init__.py
pylibchorus/chorus_api.py
pylibchorus/version.py
pylibchorus.egg-info/PKG-INFO
pylibchorus.egg-info/SOURCES.txt
pylibchorus.egg-info/dependency_links.txt
pylibchorus.egg-info/requires.txt
pylibchorus.egg-info/top_level.txt
pylibchorus/tests/__init__.py
pylibchorus/tests/chorus_client_tests.py